MANIFEST.in
README.rst
setup.cfg
setup.py
docs/HISTORY.txt
docs/INSTALL.txt
docs/LICENSE.GPL
docs/LICENSE.txt
seantis/__init__.py
seantis.dir.base.egg-info/PKG-INFO
seantis.dir.base.egg-info/SOURCES.txt
seantis.dir.base.egg-info/dependency_links.txt
seantis.dir.base.egg-info/entry_points.txt
seantis.dir.base.egg-info/namespace_packages.txt
seantis.dir.base.egg-info/not-zip-safe
seantis.dir.base.egg-info/requires.txt
seantis.dir.base.egg-info/top_level.txt
seantis/dir/__init__.py
seantis/dir/base/__init__.py
seantis/dir/base/allkeys.txt
seantis/dir/base/behavior.py
seantis/dir/base/catalog.py
seantis/dir/base/configure.zcml
seantis/dir/base/const.py
seantis/dir/base/core.py
seantis/dir/base/directory.py
seantis/dir/base/fieldmap.py
seantis/dir/base/interfaces.py
seantis/dir/base/item.py
seantis/dir/base/macros.py
seantis/dir/base/pyuca.py
seantis/dir/base/session.py
seantis/dir/base/setuphandlers.py
seantis/dir/base/subscribers.py
seantis/dir/base/upgrades.py
seantis/dir/base/upgrades.zcml
seantis/dir/base/utils.py
seantis/dir/base/xlsexport.py
seantis/dir/base/xlsimport.py
seantis/dir/base/css/directory.css
seantis/dir/base/css/print.css
seantis/dir/base/css/search.css
seantis/dir/base/css/token-input.css
seantis/dir/base/images/markers.psd
seantis/dir/base/images/singlemarker.png
seantis/dir/base/images/markers/marker-A.png
seantis/dir/base/images/markers/marker-B.png
seantis/dir/base/images/markers/marker-C.png
seantis/dir/base/images/markers/marker-D.png
seantis/dir/base/images/markers/marker-E.png
seantis/dir/base/images/markers/marker-F.png
seantis/dir/base/images/markers/marker-G.png
seantis/dir/base/images/markers/marker-H.png
seantis/dir/base/images/markers/marker-I.png
seantis/dir/base/images/markers/marker-J.png
seantis/dir/base/images/markers/marker-K.png
seantis/dir/base/images/markers/marker-L.png
seantis/dir/base/images/markers/marker-M.png
seantis/dir/base/images/markers/marker-N.png
seantis/dir/base/images/markers/marker-O.png
seantis/dir/base/images/markers/marker-P.png
seantis/dir/base/images/markers/marker-Q.png
seantis/dir/base/images/markers/marker-R.png
seantis/dir/base/images/markers/marker-S.png
seantis/dir/base/images/markers/marker-T.png
seantis/dir/base/images/markers/marker-U.png
seantis/dir/base/images/markers/marker-V.png
