Metadata-Version: 1.1
Name: seantis.dir.base
Version: 1.10.1
Summary: Directory module for Plone using Dexterity
Home-page: https://github.com/seantis/seantis.dir.base
Author: Seantis GmbH
Author-email: info@seantis.ch
License: GPL v2
Keywords: directory plone dexterity
Platform: UNKNOWN
Classifier: Framework :: Plone
Classifier: Framework :: Plone :: 4.3
Classifier: Intended Audience :: Developers
Classifier: Topic :: Software Development :: Libraries :: Python Modules
Classifier: Programming Language :: Python
